bigframes/__init__.py
bigframes/_importing.py
bigframes/clients.py
bigframes/constants.py
bigframes/dataframe.py
bigframes/dtypes.py
bigframes/enums.py
bigframes/exceptions.py
bigframes/features.py
bigframes/formatting_helpers.py
bigframes/py.typed
bigframes/series.py
bigframes/version.py
bigframes/_config/__init__.py
bigframes/_config/auth.py
bigframes/_config/bigquery_options.py
bigframes/_config/compute_options.py
bigframes/_config/display_options.py
bigframes/_config/experiment_options.py
bigframes/_config/global_options.py
bigframes/_config/sampling_options.py
bigframes/_tools/__init__.py
bigframes/_tools/strings.py
bigframes/bigquery/__init__.py
bigframes/bigquery/ai.py
bigframes/bigquery/ml.py
bigframes/bigquery/_operations/__init__.py
bigframes/bigquery/_operations/ai.py
bigframes/bigquery/_operations/approx_agg.py
bigframes/bigquery/_operations/array.py
bigframes/bigquery/_operations/datetime.py
bigframes/bigquery/_operations/geo.py
bigframes/bigquery/_operations/json.py
bigframes/bigquery/_operations/ml.py
bigframes/bigquery/_operations/search.py
bigframes/bigquery/_operations/sql.py
bigframes/bigquery/_operations/struct.py
bigframes/blob/_functions.py
bigframes/core/__init__.py
bigframes/core/agg_expressions.py
bigframes/core/array_value.py
bigframes/core/backports.py
bigframes/core/bigframe_node.py
bigframes/core/block_transforms.py
bigframes/core/blocks.py
bigframes/core/bq_data.py
bigframes/core/convert.py
bigframes/core/eval.py
bigframes/core/events.py
bigframes/core/explode.py
bigframes/core/expression.py
bigframes/core/expression_factoring.py
bigframes/core/field.py
bigframes/core/global_session.py
bigframes/core/graphs.py
bigframes/core/guid.py
bigframes/core/identifiers.py
bigframes/core/indexers.py
bigframes/core/interchange.py
bigframes/core/join_def.py
bigframes/core/local_data.py
bigframes/core/log_adapter.py
bigframes/core/nodes.py
bigframes/core/ordered_sets.py
bigframes/core/ordering.py
bigframes/core/pruning.py
bigframes-2.32.0.dist-info/licenses/LICENSE
bigframes-2.32.0.dist-info/METADATA
bigframes-2.32.0.dist-info/WHEEL
bigframes-2.32.0.dist-info/top_level.txt
bigframes-2.32.0.dist-info/RECORD
