Metadata-Version: 2.4
Name: bigframes
Version: 2.32.0
Summary: BigQuery DataFrames -- scalable analytics and machine learning with BigQuery
Home-page: https://github.com/googleapis/python-bigquery-dataframes
Author: Google LLC
Author-email: bigframes-feedback@google.com
License: Apache 2.0
Platform: Posix; MacOS X; Windows
Classifier: Development Status :: 5 - Production/Stable
Classifier: Intended Audience :: Developers
Classifier: License :: OSI Approved :: Apache Software License
Classifier: Programming Language :: Python
Classifier: Programming Language :: Python :: 3
Classifier: Programming Language :: Python :: 3.9
Classifier: Programming Language :: Python :: 3.10
Classifier: Programming Language :: Python :: 3.11
Classifier: Programming Language :: Python :: 3.12
Classifier: Programming Language :: Python :: 3.13
Classifier: Operating System :: OS Independent
Classifier: Topic :: Internet
Requires-Python: >=3.9
License-File: LICENSE
Requires-Dist: cloudpickle>=2.0.0
Requires-Dist: fsspec>=2023.3.0
Requires-Dist: gcsfs!=2025.5.0,>=2023.3.0
Requires-Dist: geopandas>=0.12.2
Requires-Dist: google-auth<3.0,>=2.15.0
Requires-Dist: google-cloud-bigquery[bqstorage,pandas]>=3.36.0
Requires-Dist: google-cloud-bigquery-storage<3.0.0,>=2.30.0
Requires-Dist: google-cloud-functions>=1.12.0
Requires-Dist: google-cloud-bigquery-connection>=1.12.0
Requires-Dist: google-cloud-resource-manager>=1.10.3
Requires-Dist: google-cloud-storage>=2.0.0
Requires-Dist: grpc-google-iam-v1>=0.14.2
Requires-Dist: numpy>=1.24.0
Requires-Dist: pandas>=1.5.3
Requires-Dist: pandas-gbq>=0.26.1
Requires-Dist: pyarrow>=15.0.2
Requires-Dist: pydata-google-auth>=1.8.2
Requires-Dist: requests>=2.27.1
Requires-Dist: shapely>=1.8.5
Requires-Dist: tabulate>=0.9
Requires-Dist: ipywidgets>=7.7.1
Requires-Dist: humanize>=4.6.0
Requires-Dist: matplotlib>=3.7.1
Requires-Dist: db-dtypes>=1.4.2
Requires-Dist: atpublic<6,>=2.3
Requires-Dist: python-dateutil<3,>=2.8.2
Requires-Dist: pytz>=2022.7
Requires-Dist: toolz<2,>=0.11
Requires-Dist: typing-extensions<5,>=4.5.0
Requires-Dist: rich<14,>=12.4.4
Provides-Extra: tests
Requires-Dist: freezegun; extra == "tests"
Requires-Dist: pytest-snapshot; extra == "tests"
Requires-Dist: google-cloud-bigtable>=2.24.0; extra == "tests"
Requires-Dist: google-cloud-pubsub>=2.21.4; extra == "tests"
Provides-Extra: polars
Requires-Dist: polars>=1.21.0; extra == "polars"
Provides-Extra: scikit-learn
Requires-Dist: scikit-learn>=1.2.2; extra == "scikit-learn"
Provides-Extra: dev
Requires-Dist: pytest; extra == "dev"
Requires-Dist: pre-commit; extra == "dev"
Requires-Dist: nox; extra == "dev"
Requires-Dist: google-cloud-testutils; extra == "dev"
Provides-Extra: anywidget
Requires-Dist: anywidget>=0.9.18; extra == "anywidget"
Requires-Dist: traitlets>=5.0.0; extra == "anywidget"
Provides-Extra: all
Requires-Dist: anywidget>=0.9.18; extra == "all"
Requires-Dist: freezegun; extra == "all"
Requires-Dist: google-cloud-bigtable>=2.24.0; extra == "all"
Requires-Dist: google-cloud-pubsub>=2.21.4; extra == "all"
Requires-Dist: google-cloud-testutils; extra == "all"
Requires-Dist: nox; extra == "all"
Requires-Dist: polars>=1.21.0; extra == "all"
Requires-Dist: pre-commit; extra == "all"
Requires-Dist: pytest; extra == "all"
Requires-Dist: pytest-snapshot; extra == "all"
Requires-Dist: scikit-learn>=1.2.2; extra == "all"
Requires-Dist: traitlets>=5.0.0; extra == "all"
Dynamic: author
Dynamic: author-email
Dynamic: classifier
Dynamic: description
Dynamic: description-content-type
Dynamic: home-page
Dynamic: license
Dynamic: license-file
Dynamic: platform
Dynamic: provides-extra
Dynamic: requires-dist
Dynamic: requires-python
Dynamic: summary
